dianzhong/__init__.py
dianzhong/basic.py
dianzhong-0.0.2.dist-info/METADATA
dianzhong-0.0.2.dist-info/WHEEL
dianzhong-0.0.2.dist-info/top_level.txt
dianzhong-0.0.2.dist-info/RECORD
