Metadata-Version: 2.1
Name: dianzhong
Version: 0.0.2
Summary: 点众平台SDK
Home-page: https://gitee.com/ZeroSeeker/dianzhong
Author: ZeroSeeker
Author-email: zeroseeker@foxmail.com
License: UNKNOWN
Platform: UNKNOWN
Classifier: Programming Language :: Python :: 3
Classifier: License :: OSI Approved :: MIT License
Classifier: Operating System :: OS Independent
Requires-Dist: lazysdk (==0.0.9)
